nbplus-0.0.80.data/data/etc/jupyter/nbconfig/notebook.d/nbplusplus.json
nbplus-0.0.80.data/data/share/jupyter/kernels/nbplusplus/kernel.json
nbplus-0.0.80.data/data/share/jupyter/kernels/nbplusplus/logo-32x32.png
nbplus-0.0.80.data/data/share/jupyter/kernels/nbplusplus/logo-64x64.png
nbplus-0.0.80.data/data/share/jupyter/labextensions/jupyterlab-nbplusplus/package.json
nbplus-0.0.80.data/data/share/jupyter/labextensions/jupyterlab-nbplusplus/static/549.c5e31d09923c72d47fac.js
nbplus-0.0.80.data/data/share/jupyter/labextensions/jupyterlab-nbplusplus/static/568.e49e9af7479bf07ca2dd.js
nbplus-0.0.80.data/data/share/jupyter/labextensions/jupyterlab-nbplusplus/static/remoteEntry.68632b8bd19cf28f4ec0.js
nbplus-0.0.80.data/data/share/jupyter/labextensions/jupyterlab-nbplusplus/static/style.js
nbplus-0.0.80.data/data/share/jupyter/labextensions/jupyterlab-nbplusplus/static/third-party-licenses.json
nbplus-0.0.80.data/data/share/jupyter/nbextensions/nbplusplus/index.js
nbplus-0.0.80.data/data/share/jupyter/nbextensions/nbplusplus/index.js.map
nbplusplus/__init__.py
nbplusplus/_version.py
nbplusplus/extra_builtins.py
nbplusplus/install.py
nbplusplus/ipython_utils.py
nbplusplus/line_magics.py
nbplusplus/run_mode.py
nbplusplus/safety.py
nbplusplus/singletons.py
nbplusplus/types.py
nbplusplus/version.py
nbplusplus/analysis/__init__.py
nbplusplus/analysis/live_refs.py
nbplusplus/analysis/mixins.py
nbplusplus/analysis/reactive_modifiers.py
nbplusplus/analysis/resolved_symbols.py
nbplusplus/analysis/slicing.py
nbplusplus/analysis/symbol_edges.py
nbplusplus/analysis/symbol_ref.py
nbplusplus/analysis/utils.py
nbplusplus/data_model/__init__.py
nbplusplus/data_model/annotation_utils.py
nbplusplus/data_model/code_cell.py
nbplusplus/data_model/data_symbol.py
nbplusplus/data_model/namespace.py
nbplusplus/data_model/scope.py
nbplusplus/data_model/sizing.py
nbplusplus/data_model/timestamp.py
nbplusplus/data_model/update_protocol.py
nbplusplus/kernel/__init__.py
nbplus-0.0.80.dist-info/LICENSE.txt
nbplus-0.0.80.dist-info/METADATA
nbplus-0.0.80.dist-info/WHEEL
nbplus-0.0.80.dist-info/top_level.txt
nbplus-0.0.80.dist-info/RECORD
